filterlib/__init__.py
filterlib/filter.py
filterlib/filtermodule.py
filterlib-0.1.2.dist-info/LICENSE
filterlib-0.1.2.dist-info/METADATA
filterlib-0.1.2.dist-info/WHEEL
filterlib-0.1.2.dist-info/top_level.txt
filterlib-0.1.2.dist-info/RECORD
