Metadata-Version: 2.1
Name: filterlib
Version: 0.1.2
Summary: A filter library for python
Home-page: https://gitlab.com/Raspilot/filterlib
Author: Fabian Becker
Author-email: fab.becker@outlook.de
License: UNKNOWN
Platform: UNKNOWN
Classifier: Programming Language :: Python :: 3
Classifier: License :: OSI Approved :: GNU General Public License v3 (GPLv3)
Classifier: Operating System :: OS Independent
Requires-Python: >=3.6
